passgenr/__init__.py
passgenr/passgenr.py
passgenr-0.0.2.dist-info/METADATA
passgenr-0.0.2.dist-info/WHEEL
passgenr-0.0.2.dist-info/top_level.txt
passgenr-0.0.2.dist-info/RECORD
